[{"ID":229,"DATE":"5 Januari 2018","CITY":"Musi Rawas","PROVINCE":"Sumatera Selatan","PERSECUTOR":"4 oknum Satlantas Polres Musi Rawas","VICTIM":"Faruq (16)","NUMBER_OF_VICTIM":1,"CASE":"Razia kendaraan","METODE":"Ditendang","METODE_PENYIKSAAN":"Korban mengalami luka parah akibat diborgol dan dipukuli","EFFECT":"Luka"},{"ID":230,"DATE":"1 Februari 2018","CITY":"Kalidoni","PROVINCE":"Sumatera Selatan","PERSECUTOR":"Iptu Sudani","VICTIM":"Eko Yuliono (37)","NUMBER_OF_VICTIM":1,"CASE":"Pencurian","METODE":"Dipukul","METODE_PENYIKSAAN":"Korban mengalami luka akibat penyiksaan","EFFECT":"Luka"},{"ID":231,"DATE":"11 Februari 2018","CITY":"Jeneponto","PROVINCE":"Sulawesi Selatan","PERSECUTOR":"Polres Jeneponto","VICTIM":"Awing (42)","NUMBER_OF_VICTIM":1,"CASE":"Pencurian sepeda motor","METODE":"Ditembak","METODE_PENYIKSAAN":"Korban tewas dalam penahanan","EFFECT":"Meninggal"},{"ID":232,"DATE":"8 Februari 2018","CITY":"Nias","PROVINCE":"Sumatera Utara","PERSECUTOR":"BNN Mabes Polri","VICTIM":"Kasiruddin Zendrato","NUMBER_OF_VICTIM":1,"CASE":"Bandar narkoba","METODE":"Ditendang","METODE_PENYIKSAAN":"Korban mengalami luka akibat pukulan dan tendangan aparat","EFFECT":"Luka"},{"ID":233,"DATE":"7 Februari 2018","CITY":"Lampung Tengah","PROVINCE":"Lampung","PERSECUTOR":"Aiptu NY, Brigpol RK, dan Brigpol AY","VICTIM":"Pengabdi Bapib (38)","NUMBER_OF_VICTIM":1,"CASE":"Tindak kriminal","METODE":"Dipukul","METODE_PENYIKSAAN":"Korban mengalami luka akibat pemukulan dan penyiksaan","EFFECT":"Luka"},{"ID":234,"DATE":"7 Februari 2018","CITY":"Indramayu","PROVINCE":"Jawa Barat","PERSECUTOR":"Densus 88 AT Mabes Polri","VICTIM":"MJ 31","NUMBER_OF_VICTIM":1,"CASE":"Terduga teroris","METODE":"Ditembak","METODE_PENYIKSAAN":"Korban tewas akibat penyiksaan","EFFECT":"Meninggal"},{"ID":235,"DATE":"10 Februari 2018","CITY":"Pasaman Barat","PROVINCE":"Sumatera Barat","PERSECUTOR":"SF","VICTIM":"Yogi Saputra (20)","NUMBER_OF_VICTIM":1,"CASE":"Pencurian","METODE":"Dibakar","METODE_PENYIKSAAN":"Korban kritis akibat pemukulan bertubi-tubi","EFFECT":"Luka"},{"ID":236,"DATE":"14 Februari 2018","CITY":"Medan Marelan","PROVINCE":"Sumatera Utara","PERSECUTOR":"oknum Polsek Medan Labuhan","VICTIM":"Bambang Pujiono (30)","NUMBER_OF_VICTIM":1,"CASE":"Pencurian","METODE":"Ditendang","METODE_PENYIKSAAN":"Korban tewas akibat penyiksaan","EFFECT":"Meninggal"},{"ID":237,"DATE":"14 Februari 2018","CITY":"Sukadana","PROVINCE":"Kalimantan Selatan","PERSECUTOR":"Polres Kayong Utara","VICTIM":"Abdul Hamid dan 10 orang","NUMBER_OF_VICTIM":11,"CASE":"Tawuran","METODE":"Dipukul","METODE_PENYIKSAAN":"Korban mengalami luka parah akibat penyiksaan","EFFECT":"Luka"},{"ID":238,"DATE":"15 Februari 2018","CITY":"Lampung Timur","PROVINCE":"Lampung","PERSECUTOR":"DD, WT","VICTIM":"Ahmad Ali Mukmin 24","NUMBER_OF_VICTIM":1,"CASE":"Tindak kriminal","METODE":"Dipukul","METODE_PENYIKSAAN":"Korban mengalami luka pada bagian kepala dan dada","EFFECT":"Luka"},{"ID":239,"DATE":"15 Februari 2018","CITY":"Kalidoni","PROVINCE":"Sumatera Selatan","PERSECUTOR":"Bripka IK","VICTIM":"M Sobirin (32)","NUMBER_OF_VICTIM":1,"CASE":"Kepemilikan narkoba","METODE":"Dipukul","METODE_PENYIKSAAN":"Ketiga oknum polisi memukuli korban hingga mengalami luka di leher serta memar di kepala, jari tangan, pinggang, dan sakit di bagian kemaluan","EFFECT":"Luka"},{"ID":240,"DATE":"21 Februari 2018","CITY":"Pasangkayu","PROVINCE":"Sulawesi Barat","PERSECUTOR":"Oknum Polres Pasangkayu, GD","VICTIM":"AD","NUMBER_OF_VICTIM":1,"CASE":"Penikaman","METODE":"Ditendang","METODE_PENYIKSAAN":"Korban disiksa hingga sesak nafas","EFFECT":"Luka"},{"ID":241,"DATE":"20 Maret 2018","CITY":"Sorong","PROVINCE":"Papua","PERSECUTOR":"Polres Kota Sorang","VICTIM":"Rico 17","NUMBER_OF_VICTIM":1,"CASE":"Pencurian","METODE":"Dipukul","METODE_PENYIKSAAN":"Korban tewas akibat penyiksaan","EFFECT":"Meninggal"},{"ID":242,"DATE":"14 Maret 2018","CITY":"Muna","PROVINCE":"Sulawesi Tenggara","PERSECUTOR":"Polres Muna","VICTIM":"Ivhan 14","NUMBER_OF_VICTIM":1,"CASE":"Tindak anarkis","METODE":"Ditendang","METODE_PENYIKSAAN":"Korban mengalami luka parah pada bagian wajah","EFFECT":"Luka"},{"ID":243,"DATE":"2 April 2018","CITY":"Singkil","PROVINCE":"Aceh","PERSECUTOR":"Oknum Polres Singkil","VICTIM":"Ade Setiawan","NUMBER_OF_VICTIM":1,"CASE":"Pencurian besi","METODE":"Dipukul","METODE_PENYIKSAAN":"Korban mengalami luka pada bagian dada","EFFECT":"Luka"},{"ID":244,"DATE":"5 April 2018","CITY":"Mesuji","PROVINCE":"Lampung","PERSECUTOR":"3 oknum Polres Mesuji","VICTIM":"Katenun (39)","NUMBER_OF_VICTIM":1,"CASE":"Diduga memiliki narkoba","METODE":"Dicekik","METODE_PENYIKSAAN":"Korban mengalami beberapa luka lebam di bagian kepala, telinga, wajah serta punggung. Korban juga kehilangan uang sebesar Rp50 juta akibat pemerasan yang dilakukan tiga oknum polisi","EFFECT":"Luka"},{"ID":245,"DATE":"13 April 2018","CITY":"Medan","PROVINCE":"Sumatera Utara","PERSECUTOR":"Moris Hutapea","VICTIM":"Elito Putra 25","NUMBER_OF_VICTIM":1,"CASE":"Tindak kekerasan","METODE":"Dipukul","METODE_PENYIKSAAN":"Korban disiksa hingga mengalami pendarahan","EFFECT":"Luka"},{"ID":246,"DATE":"13 April 2018","CITY":"Wajo","PROVINCE":"Sulawesi Selatan","PERSECUTOR":"Anggota Polres Wajo","VICTIM":"Sakkir","NUMBER_OF_VICTIM":1,"CASE":"Konvoi","METODE":"Dipukul","METODE_PENYIKSAAN":"Korban mengalami penangkapan sewenang-wenang dan penyiksaan","EFFECT":"Luka"},{"ID":247,"DATE":"13 April 2018","CITY":"Wajo","PROVINCE":"Sulawesi Selatan","PERSECUTOR":"Anggota Polres Wajo","VICTIM":"Hasbi","NUMBER_OF_VICTIM":1,"CASE":"Konvoi","METODE":"Dipukul","METODE_PENYIKSAAN":"Korban mengalami penangkapan sewenang-wenang dan penyiksaan","EFFECT":"Luka"},{"ID":248,"DATE":"13 April 2018","CITY":"Wajo","PROVINCE":"Sulawesi Selatan","PERSECUTOR":"Anggota Polres Wajo","VICTIM":"Rifki","NUMBER_OF_VICTIM":1,"CASE":"Konvoi","METODE":"Dipukul","METODE_PENYIKSAAN":"Korban mengalami penangkapan sewenang-wenang dan penyiksaan","EFFECT":"Luka"},{"ID":249,"DATE":"13 April 2018","CITY":"Wajo","PROVINCE":"Sulawesi Selatan","PERSECUTOR":"Anggota Polres Wajo","VICTIM":"Sayyu","NUMBER_OF_VICTIM":1,"CASE":"Konvoi","METODE":"Dipukul","METODE_PENYIKSAAN":"Korban mengalami penangkapan sewenang-wenang dan penyiksaan","EFFECT":"Luka"},{"ID":250,"DATE":"13 April 2018","CITY":"Wajo","PROVINCE":"Sulawesi Selatan","PERSECUTOR":"Anggota Polres Wajo","VICTIM":"Ciwan","NUMBER_OF_VICTIM":1,"CASE":"Konvoi","METODE":"Dipukul","METODE_PENYIKSAAN":"Korban mengalami penangkapan sewenang-wenang dan penyiksaan","EFFECT":"Luka"},{"ID":251,"DATE":"13 April 2018","CITY":"Wajo","PROVINCE":"Sulawesi Selatan","PERSECUTOR":"Anggota Polres Wajo","VICTIM":"Safar","NUMBER_OF_VICTIM":1,"CASE":"Konvoi","METODE":"Dipukul","METODE_PENYIKSAAN":"Korban mengalami penangkapan sewenang-wenang dan penyiksaan","EFFECT":"Luka"},{"ID":252,"DATE":"03 Mei 2018","CITY":"Bulukumba","PROVINCE":"Sulawesi Selatan","PERSECUTOR":"Aiptu AK","VICTIM":"A. Arya 17","NUMBER_OF_VICTIM":1,"CASE":"Perusakan cafe","METODE":"Diseret","METODE_PENYIKSAAN":"Korban mengalami luka di sekujur tubuh","EFFECT":"Luka"},{"ID":253,"DATE":"03 Mei 2018","CITY":"Sidrap","PROVINCE":"Sulawesi Selatan","PERSECUTOR":"AT","VICTIM":"Sudirman alias Ladalle (41)","NUMBER_OF_VICTIM":1,"CASE":"Pencurian","METODE":"Dipukul","METODE_PENYIKSAAN":"Korban mengalami luka akibat penyiksaan","EFFECT":"Luka"},{"ID":254,"DATE":"05 Mei 2018","CITY":"Jayapura","PROVINCE":"Papua","PERSECUTOR":"Oknum Polres Deiyai","VICTIM":"Mando Mote","NUMBER_OF_VICTIM":1,"CASE":"Pencurian","METODE":"Dicekik","METODE_PENYIKSAAN":"Korban mengalami luka-luka akibat dipukul dengan senjata api","EFFECT":"Luka"},{"ID":255,"DATE":"05 Mei 2018","CITY":"Jayapura","PROVINCE":"Papua","PERSECUTOR":"Oknum Polres Deiyai","VICTIM":"Jubi Abeth Youw","NUMBER_OF_VICTIM":1,"CASE":"Pencurian","METODE":"Dicekik","METODE_PENYIKSAAN":"Korban mengalami luka-luka akibat dipukul dengan senjata api","EFFECT":"Luka"},{"ID":256,"DATE":"08 Mei 2018","CITY":"Ternate","PROVINCE":"Maluku Utara","PERSECUTOR":"Bripda Fajrul","VICTIM":"3 Tahanan","NUMBER_OF_VICTIM":3,"CASE":"Pencurian","METODE":"Dipukul","METODE_PENYIKSAAN":"Korban mengalami luka akibat penyiksaan","EFFECT":"Luka"},{"ID":257,"DATE":"13 Mei 2018","CITY":"Medan","PROVINCE":"Sumatera Utara","PERSECUTOR":"Brigadir Z","VICTIM":"Bambang Sujatmiko","NUMBER_OF_VICTIM":1,"CASE":"Judi","METODE":"Dipukul","METODE_PENYIKSAAN":"Korban mengalami tindak penyiksaan dan luka-luka","EFFECT":"Luka"},{"ID":258,"DATE":"13 Mei 2018","CITY":"Medan","PROVINCE":"Sumatera Utara","PERSECUTOR":"Brigadir Z","VICTIM":"Ifan","NUMBER_OF_VICTIM":1,"CASE":"Judi","METODE":"Dipukul","METODE_PENYIKSAAN":"Korban mengalami tindak penyiksaan dan luka-luka","EFFECT":"Luka"},{"ID":259,"DATE":"13 Mei 2018","CITY":"Medan","PROVINCE":"Sumatera Utara","PERSECUTOR":"Brigadir Z","VICTIM":"Parlindungan Harahap","NUMBER_OF_VICTIM":1,"CASE":"Judi","METODE":"Dipukul","METODE_PENYIKSAAN":"Korban mengalami tindak penyiksaan dan luka-luka","EFFECT":"Luka"},{"ID":260,"DATE":"13 Mei 2018","CITY":"Medan","PROVINCE":"Sumatera Utara","PERSECUTOR":"Brigadir Z","VICTIM":"Rahmad Habibullah","NUMBER_OF_VICTIM":1,"CASE":"Judi","METODE":"Dipukul","METODE_PENYIKSAAN":"Korban mengalami tindak penyiksaan dan luka-luka","EFFECT":"Luka"},{"ID":261,"DATE":"13 Mei 2018","CITY":"Medan","PROVINCE":"Sumatera Utara","PERSECUTOR":"Brigadir Z","VICTIM":"Aspin Fauzi","NUMBER_OF_VICTIM":1,"CASE":"Judi","METODE":"Dipukul","METODE_PENYIKSAAN":"Korban mengalami tindak penyiksaan dan luka-luka","EFFECT":"Luka"},{"ID":262,"DATE":"15 Mei 2018","CITY":"Gianyar","PROVINCE":"Bali","PERSECUTOR":"SH","VICTIM":"SH 35","NUMBER_OF_VICTIM":1,"CASE":"Pencurian","METODE":"Memukul, membakar","METODE_PENYIKSAAN":"Selain pergelangan tangan, kata Muhyiddin, dada korban juga lebam. Kemudian korban mengaku kepada Muhyiddin alat kelaminnya diteteskan plastik yang terbakar.","EFFECT":"Luka"},{"ID":263,"DATE":"22 Mei 2018","CITY":"Bantaeng","PROVINCE":"Sulawesi Selatan","PERSECUTOR":"Oknum Polres Bantaeng","VICTIM":"Sangkala (39)","NUMBER_OF_VICTIM":1,"CASE":"Pencurian mobil","METODE":"Dipukul","METODE_PENYIKSAAN":"Korban tewas akibat penyiksaan","EFFECT":"Meninggal"},{"ID":264,"DATE":"22 Mei 2018","CITY":"Manokwari","PROVINCE":"Papua","PERSECUTOR":"EK, N","VICTIM":"Valen Kabiay (17)","NUMBER_OF_VICTIM":1,"CASE":"Diduga terlibat penjambretan","METODE":"Dipukul","METODE_PENYIKSAAN":"Korban mengalami luka akibat penyiksaan","EFFECT":"Luka"},{"ID":265,"DATE":"22 Mei 2018","CITY":"Manokwari","PROVINCE":"Papua","PERSECUTOR":"EK, N","VICTIM":"Rio Sanggemi (16)","NUMBER_OF_VICTIM":1,"CASE":"Diduga terlibat penjambretan","METODE":"Dipukul","METODE_PENYIKSAAN":"Korban mengalami luka akibat penyiksaan","EFFECT":"Luka"},{"ID":266,"DATE":"28 Mei 2018","CITY":"Tobasa","PROVINCE":"Sumatera Utara","PERSECUTOR":"JS","VICTIM":"SS (43)","NUMBER_OF_VICTIM":1,"CASE":"Pencurian","METODE":"Dipukul","METODE_PENYIKSAAN":"Pelaku mengambil sebuah kursi bulat besi dan menghantam ke kepala sebelah kiri korban hingga sobek mengeluarkan darah. Korban mengalami luka sobek dan dilarikan warga ke kontrakannya.","EFFECT":"Luka"},{"ID":267,"DATE":"1 Juni 2018","CITY":"Desa Suppa, Kecamatan Suppa, Kabupaten Pinrang","PROVINCE":"Sulawesi Selatan","PERSECUTOR":"Polres Barru","VICTIM":"Muin (45)","NUMBER_OF_VICTIM":1,"CASE":"Pencurian","METODE":"Disetrum","METODE_PENYIKSAAN":"Korban mengalami luka akibat Diseret dan dipukuli","EFFECT":"Luka"},{"ID":268,"DATE":"5 Juni 2018","CITY":"Bajawa","PROVINCE":"Nusa Tenggara Timur","PERSECUTOR":"Polsek Soa, Kamelus Tokan","VICTIM":"Hendrik Jehurut (60)","NUMBER_OF_VICTIM":1,"CASE":"Miras","METODE":"Ditendang","METODE_PENYIKSAAN":"Korban ditelanjangi dan dipukuli","EFFECT":"Luka"},{"ID":269,"DATE":"20 Juni 2018","CITY":"Bantaeng","PROVINCE":"Sulawesi Selatan","PERSECUTOR":"Polres Bantaeng, inisial B","VICTIM":"IlhamSAH, Ikbal (23), Bantaeng","NUMBER_OF_VICTIM":1,"CASE":"Money politic","METODE":"    ","METODE_PENYIKSAAN":"Korban mengalami luka bakar di bagian telinga akibat disiksa","EFFECT":"Luka"},{"ID":270,"DATE":"20 Juni 2018","CITY":"Sorolnagun","PROVINCE":"Sumatera Barat","PERSECUTOR":"Polsek Mandiangin","VICTIM":"Diwun","NUMBER_OF_VICTIM":1,"CASE":"Pencurian","METODE":"Ditembak","METODE_PENYIKSAAN":"Korban tewas dengan 24 luka tembak","EFFECT":"Meninggal"},{"ID":271,"DATE":"08 Juli 2018","CITY":"Gianyar","PROVINCE":"Bali","PERSECUTOR":"Bripda PT Khrisna Wahyudi Suputra, Bripda KDK Agus Wiratha, dan Bripda I Gede Agus Apriyog, Polda Bali","VICTIM":"Dimas Purwadipa (22)","NUMBER_OF_VICTIM":1,"CASE":"Pencurian","METODE":"Ditendang","METODE_PENYIKSAAN":"Korban babak belur dan mengalami pendarahan","EFFECT":"Luka"},{"ID":272,"DATE":"09 Juli 2018","CITY":"Morowali","PROVINCE":"Sulawesi Tengah","PERSECUTOR":"Personel BKO Polda Sulawesi Tengah (Sulteng)","VICTIM":"Muhammad Rizchal (21)","NUMBER_OF_VICTIM":1,"CASE":"Salah tangkap","METODE":"Ditendang","METODE_PENYIKSAAN":"Korban mengalami luka lebam di bagian mata kiri dan pundak kiri serta sobek pada kepala dan telinga bagian kanan","EFFECT":"Luka"},{"ID":273,"DATE":"09 Juli 2018","CITY":"Medan","PROVINCE":"Sumatera Utara","PERSECUTOR":"Polres Medan Kota","VICTIM":"Wanda Gunawan Pasaribu","NUMBER_OF_VICTIM":1,"CASE":"Pencurian handphone","METODE":"Ditembak","METODE_PENYIKSAAN":"Korban mengalami luka tembak di kedua kaki","EFFECT":"Luka"},{"ID":274,"DATE":"13 Juli 2018","CITY":"Blitar","PROVINCE":"Jawa Timur","PERSECUTOR":"Polsek Garum, Bripda C","VICTIM":"Raka (15)","NUMBER_OF_VICTIM":1,"CASE":"Masuk rumah dan memegang mobil salah satu anggota Polres Blitar berinisial C","METODE":"Dipukul","METODE_PENYIKSAAN":"Korban babak belur akibat penyiksaan","EFFECT":"Luka"},{"ID":275,"DATE":"18 Juli 2018","CITY":"Subang","PROVINCE":"Jawa Barat","PERSECUTOR":"3 Oknum Polda Jabar","VICTIM":"Ade Diding","NUMBER_OF_VICTIM":1,"CASE":"Penganiayaan","METODE":"Dipukul","METODE_PENYIKSAAN":"Korban tewas akibat penyiksaan","EFFECT":"Meninggal"},{"ID":276,"DATE":"19 Juli 2018","CITY":"Parepare","PROVINCE":"Sulawesi Selatan","PERSECUTOR":"Oknum Polres Parepare","VICTIM":"Muin","NUMBER_OF_VICTIM":1,"CASE":"Salah tangkap","METODE":"Disetrum","METODE_PENYIKSAAN":"Korban terluka akibat setruman","EFFECT":"Luka"},{"ID":277,"DATE":"6 Agustus 2018","CITY":"Kota Batam","PROVINCE":"Kepulauan Riau","PERSECUTOR":"4 oknum anggota Polsek Batu Aji","VICTIM":"Ferdelis Boruguru 23","NUMBER_OF_VICTIM":1,"CASE":"Salah tangkap pelaku pembacokan","METODE":"Dipukul","METODE_PENYIKSAAN":"Korban terluka akibat dipukuli dan disiram","EFFECT":"Luka"},{"ID":278,"DATE":"16 Agustus 2018","CITY":"Medan","PROVINCE":"Sumatera Utara","PERSECUTOR":"Aparat Polsek Penyabungan","VICTIM":"Yusril Mahendra","NUMBER_OF_VICTIM":1,"CASE":"Pencurian","METODE":"Dipukul","METODE_PENYIKSAAN":"1 Tewas dan 2 lainnya luka akibat pemukulan","EFFECT":"Luka dan meninggal"},{"ID":279,"DATE":"16 Agustus 2018","CITY":"Medan","PROVINCE":"Sumatera Utara","PERSECUTOR":"Aparat Polsek Penyabungan","VICTIM":"Kaharuddin","NUMBER_OF_VICTIM":1,"CASE":"Pencurian","METODE":"Dipukul","METODE_PENYIKSAAN":"1 Tewas dan 2 lainnya luka akibat pemukulan","EFFECT":"Luka dan meninggal"},{"ID":280,"DATE":"16 Agustus 2018","CITY":"Medan","PROVINCE":"Sumatera Utara","PERSECUTOR":"Aparat Polsek Penyabungan","VICTIM":"Irsan","NUMBER_OF_VICTIM":1,"CASE":"Pencurian","METODE":"Dipukul","METODE_PENYIKSAAN":"1 Tewas dan 2 lainnya luka akibat pemukulan","EFFECT":"Luka dan meninggal"},{"ID":281,"DATE":"26 Agustus 2018","CITY":"Manokwari","PROVINCE":"Papua","PERSECUTOR":"Polsek Kota Manokwai","VICTIM":"Fery Korwa","NUMBER_OF_VICTIM":1,"CASE":"Pencurian","METODE":"Ditembak","METODE_PENYIKSAAN":"Korban terluka akibat penembakan","EFFECT":"Luka"},{"ID":282,"DATE":"26 Agustus 2018","CITY":"Kabupaten Manggarai Barat","PROVINCE":"Nusa Tenggara Timur","PERSECUTOR":"Polres Manggarai Barat","VICTIM":"One","NUMBER_OF_VICTIM":1,"CASE":"Tindak asusila","METODE":"Dipukul","METODE_PENYIKSAAN":"Korban mengalami luka akibat pemukulan","EFFECT":"Luka"},{"ID":283,"DATE":"26 Agustus 2018","CITY":"Kabupaten Manggarai Barat","PROVINCE":"Nusa Tenggara Timur","PERSECUTOR":"Polres Manggarai Barat","VICTIM":"Muhamad","NUMBER_OF_VICTIM":1,"CASE":"Tindak asusila","METODE":"Dipukul","METODE_PENYIKSAAN":"Korban mengalami luka akibat pemukulan","EFFECT":"Luka"},{"ID":284,"DATE":"26 Agustus 2018","CITY":"Kabupaten Manggarai Barat","PROVINCE":"Nusa Tenggara Timur","PERSECUTOR":"Polres Manggarai Barat","VICTIM":"Wahid","NUMBER_OF_VICTIM":6,"CASE":"Tindak asusila","METODE":"Dipukul","METODE_PENYIKSAAN":"Korban mengalami luka akibat pemukulan, 5 lainnya","EFFECT":"Luka"},{"ID":285,"DATE":"29 Agustus 2018","CITY":"Aceh Utara","PROVINCE":"Aceh","PERSECUTOR":"Aparat Polres Aceh Utara","VICTIM":"Bahagia (36)","NUMBER_OF_VICTIM":1,"CASE":"Pembunuhan","METODE":"Dipukul","METODE_PENYIKSAAN":"Korban terluka akibat penyiksaan","EFFECT":"Luka"},{"ID":286,"DATE":"29 Agustus 2018","CITY":"Aceh Utara","PROVINCE":"Aceh","PERSECUTOR":"Aparat Polres Aceh Utara","VICTIM":"Syahrur","NUMBER_OF_VICTIM":1,"CASE":"Pembunuhan","METODE":"Dipukul","METODE_PENYIKSAAN":"Korban terluka akibat penyiksaan","EFFECT":"Luka"},{"ID":287,"DATE":"29 Agustus 2018","CITY":"Aceh Utara","PROVINCE":"Aceh","PERSECUTOR":"Aparat Polres Aceh Utara","VICTIM":"1 Warga Panton","NUMBER_OF_VICTIM":1,"CASE":"Pembunuhan","METODE":"Dipukul","METODE_PENYIKSAAN":"Korban terluka akibat penyiksaan","EFFECT":"Luka"},{"ID":288,"DATE":"14 September 2018","CITY":"Makassar","PROVINCE":"Sulawesi Selatan","PERSECUTOR":"Polres Kota Makassar","VICTIM":"Ketua PMII FAI UMI","NUMBER_OF_VICTIM":1,"CASE":"Penyiksaan","METODE":"Dipukul","METODE_PENYIKSAAN":"Korban terluka akibat penyiksaan","EFFECT":"Luka"},{"ID":289,"DATE":"14 September 2018","CITY":"Makassar","PROVINCE":"Sulawesi Selatan","PERSECUTOR":"Polres Kota Makassar","VICTIM":"Fahri","NUMBER_OF_VICTIM":1,"CASE":"Penyiksaan","METODE":"Dipukul","METODE_PENYIKSAAN":"Korban terluka akibat penyiksaan","EFFECT":"Luka"},{"ID":290,"DATE":"14 September 2018","CITY":"Makassar","PROVINCE":"Sulawesi Selatan","PERSECUTOR":"Polres Kota Makassar","VICTIM":"Imam","NUMBER_OF_VICTIM":1,"CASE":"Penyiksaan","METODE":"Dipukul","METODE_PENYIKSAAN":"Korban terluka akibat penyiksaan","EFFECT":"Luka"},{"ID":291,"DATE":"14 September 2018","CITY":"Makassar","PROVINCE":"Sulawesi Selatan","PERSECUTOR":"Polres Kota Makassar","VICTIM":"Amri dan Wildan.","NUMBER_OF_VICTIM":1,"CASE":"Penyiksaan","METODE":"Dipukul","METODE_PENYIKSAAN":"Korban terluka akibat penyiksaan","EFFECT":"Luka"},{"ID":292,"DATE":"3 September 2018","CITY":"Sultra","PROVINCE":"Sulawesi Tenggara","PERSECUTOR":"Bripda Z dan Bripda F","VICTIM":"Bripda Muh. Fathurrahman Ismail","NUMBER_OF_VICTIM":1,"CASE":"Cemburu","METODE":"Dipukul","METODE_PENYIKSAAN":"Korban tewas akibat penyiksaan","EFFECT":"Meninggal"},{"ID":293,"DATE":"6 September 2018","CITY":"Batuputih","PROVINCE":"Jawa Timur","PERSECUTOR":"Polsek Batuputih","VICTIM":"MJK (16)","NUMBER_OF_VICTIM":1,"CASE":"Kerusuhan terhadap anak","METODE":"Dipukul","METODE_PENYIKSAAN":"Korban mengalami luka pada bagian mata, tangan, dan wajah","EFFECT":"Luka"},{"ID":294,"DATE":"3 September 2018","CITY":"Sumba Barat Daya","PROVINCE":"Nusa Tenggara Timur","PERSECUTOR":"Polres Sumba Barat","VICTIM":"Agustinus Anamesa (25)","NUMBER_OF_VICTIM":1,"CASE":"Tanpa memberitahukan persoalan apa","METODE":"Ditembak","METODE_PENYIKSAAN":"Korban mengalami penyiksaan dan kriminalisasi","EFFECT":"Luka"},{"ID":295,"DATE":"1 September 2018","CITY":"Aceh Utara","PROVINCE":"Aceh","PERSECUTOR":"Polres Aceh Utara","VICTIM":"Syahrul","NUMBER_OF_VICTIM":1,"CASE":"Salah tangkap pelaku pembunuhan","METODE":"Dipukul","METODE_PENYIKSAAN":"Korban mengalami pendarahan dan babak belur","EFFECT":"Luka"},{"ID":296,"DATE":"1 September 2018","CITY":"Aceh Utara","PROVINCE":"Aceh","PERSECUTOR":"Polres Aceh Utara","VICTIM":"Faisal","NUMBER_OF_VICTIM":1,"CASE":"Salah tangkap pelaku pembunuhan","METODE":"Dipukul","METODE_PENYIKSAAN":"Korban mengalami pendarahan dan babak belur","EFFECT":"Luka"},{"ID":297,"DATE":"1 September 2018","CITY":"Aceh Utara","PROVINCE":"Aceh","PERSECUTOR":"Polres Aceh Utara","VICTIM":"Bahagia","NUMBER_OF_VICTIM":1,"CASE":"Salah tangkap pelaku pembunuhan","METODE":"Dipukul","METODE_PENYIKSAAN":"Korban mengalami pendarahan dan babak belur","EFFECT":"Luka"},{"ID":298,"DATE":"13 September 2018","CITY":"Batam","PROVINCE":"Kepulauan Riau","PERSECUTOR":"Polres Batam, ED","VICTIM":"Y","NUMBER_OF_VICTIM":1,"CASE":"Diduga provokator","METODE":"Dipukul","METODE_PENYIKSAAN":"Korban ditahan dan mengalami penyiksaan","EFFECT":"Luka"},{"ID":299,"DATE":"20 September 2018","CITY":"Medan","PROVINCE":"Sumatera Utara","PERSECUTOR":"Polrestabes Medan","VICTIM":"Riza Sahputra","NUMBER_OF_VICTIM":1,"CASE":"Diduga provokator","METODE":"Dipukul","METODE_PENYIKSAAN":"Para mahasiswa mengalami luka parah akibat penganiayaan","EFFECT":"Luka"},{"ID":300,"DATE":"20 September 2018","CITY":"Medan","PROVINCE":"Sumatera Utara","PERSECUTOR":"Polrestabes Medan","VICTIM":"Dadang","NUMBER_OF_VICTIM":1,"CASE":"Diduga provokator","METODE":"Dipukul","METODE_PENYIKSAAN":"Para mahasiswa mengalami luka parah akibat penganiayaan","EFFECT":"Luka"},{"ID":301,"DATE":"20 September 2018","CITY":"Medan","PROVINCE":"Sumatera Utara","PERSECUTOR":"Polrestabes Medan","VICTIM":"Surya Darma","NUMBER_OF_VICTIM":1,"CASE":"Diduga provokator","METODE":"Dipukul","METODE_PENYIKSAAN":"Para mahasiswa mengalami luka parah akibat penganiayaan","EFFECT":"Luka"},{"ID":302,"DATE":"20 September 2018","CITY":"Medan","PROVINCE":"Sumatera Utara","PERSECUTOR":"Polrestabes Medan","VICTIM":"Amirun Salim","NUMBER_OF_VICTIM":1,"CASE":"Diduga provokator","METODE":"Dipukul","METODE_PENYIKSAAN":"Para mahasiswa mengalami luka parah akibat penganiayaan","EFFECT":"Luka"},{"ID":303,"DATE":"20 September 2018","CITY":"Medan","PROVINCE":"Sumatera Utara","PERSECUTOR":"Polrestabes Medan","VICTIM":"Fitra Lutfi","NUMBER_OF_VICTIM":1,"CASE":"Diduga provokator","METODE":"Dipukul","METODE_PENYIKSAAN":"Para mahasiswa mengalami luka parah akibat penganiayaan","EFFECT":"Luka"},{"ID":304,"DATE":"20 September 2018","CITY":"Medan","PROVINCE":"Sumatera Utara","PERSECUTOR":"Polrestabes Medan","VICTIM":"Putra Afridadi","NUMBER_OF_VICTIM":1,"CASE":"Diduga provokator","METODE":"Dipukul","METODE_PENYIKSAAN":"Para mahasiswa mengalami luka parah akibat penganiayaan","EFFECT":"Luka"},{"ID":305,"DATE":"20 September 2018","CITY":"Medan","PROVINCE":"Sumatera Utara","PERSECUTOR":"Polrestabes Medan","VICTIM":"Salim Abdurrahman","NUMBER_OF_VICTIM":1,"CASE":"Diduga provokator","METODE":"Dipukul","METODE_PENYIKSAAN":"Para mahasiswa mengalami luka parah akibat penganiayaan","EFFECT":"Luka"},{"ID":306,"DATE":"20 September 2018","CITY":"Medan","PROVINCE":"Sumatera Utara","PERSECUTOR":"Polrestabes Medan","VICTIM":"Ari","NUMBER_OF_VICTIM":1,"CASE":"Diduga provokator","METODE":"Dipukul","METODE_PENYIKSAAN":"Para mahasiswa mengalami luka parah akibat penganiayaan","EFFECT":"Luka"},{"ID":307,"DATE":"20 September 2018","CITY":"Medan","PROVINCE":"Sumatera Utara","PERSECUTOR":"Polrestabes Medan","VICTIM":"2 Orang","NUMBER_OF_VICTIM":2,"CASE":"Diduga provokator","METODE":"Dipukul","METODE_PENYIKSAAN":"Para mahasiswa mengalami luka parah akibat penganiayaan","EFFECT":"Luka"},{"ID":308,"DATE":"29 September 2018","CITY":"Tasikmalaya","PROVINCE":"Jawa Barat","PERSECUTOR":"Polres Tasikmalaya","VICTIM":"Cecep","NUMBER_OF_VICTIM":1,"CASE":"Pencurian mobil","METODE":"Ditembak","METODE_PENYIKSAAN":"Korban mengalami luka tembak di kaki kanan","EFFECT":"Luka"},{"ID":309,"DATE":"29 September 2018","CITY":"Tasikmalaya","PROVINCE":"Jawa Barat","PERSECUTOR":"Polres Tasikmalaya","VICTIM":"Wahyudin","NUMBER_OF_VICTIM":1,"CASE":"Pencurian mobil","METODE":"Ditembak","METODE_PENYIKSAAN":"Korban mengalami luka tembak di kaki kanan","EFFECT":"Luka"},{"ID":310,"DATE":"6 Oktober 2018","CITY":"Labuhan Batu","PROVINCE":"Sumatera Utara","PERSECUTOR":"Aparat Polres Labuhanbatu","VICTIM":"Suheri","NUMBER_OF_VICTIM":1,"CASE":"Pengedaran narkotika","METODE":"Dipukul","METODE_PENYIKSAAN":"Korban tewas akibat penyiksaan","EFFECT":"Meninggal"},{"ID":311,"DATE":"12 Oktober 2018","CITY":"Medan","PROVINCE":"Sumatera Utara","PERSECUTOR":"Polrestabes Medan, Iptu NI dan Iptu T","VICTIM":"Hombing","NUMBER_OF_VICTIM":1,"CASE":"Salah tangkap","METODE":"Dipukul","METODE_PENYIKSAAN":"Korban tewas akibat salah tangkap berujung penyiksaan","EFFECT":"Meninggal"},{"ID":312,"DATE":"24 Oktober 2018","CITY":"Aceh Tamiang","PROVINCE":"Aceh","PERSECUTOR":"Oknum Polsek Bendahara","VICTIM":"My","NUMBER_OF_VICTIM":1,"CASE":"Narkoba","METODE":"Dipukul","METODE_PENYIKSAAN":"Korban tewas akibat penyiksaan","EFFECT":"Meninggal"},{"ID":313,"DATE":"1 November 2018","CITY":"Banda Aceh","PROVINCE":"Aceh","PERSECUTOR":"Polres Aceh Tamiang","VICTIM":"Mahyar","NUMBER_OF_VICTIM":1,"CASE":"Narkoba","METODE":"Dipukul","METODE_PENYIKSAAN":"Korban mengalami luka lebam di perut dan kedua betis","EFFECT":"Meninggal"},{"ID":314,"DATE":"14 November 2018","CITY":"Depok","PROVINCE":"Jawa Barat","PERSECUTOR":"Oknum Polres Depok, Brimob","VICTIM":"Yulius alias Ulis","NUMBER_OF_VICTIM":1,"CASE":"Pencurian motor","METODE":"Dipukul","METODE_PENYIKSAAN":"Korban tewas akibat penyiksaan","EFFECT":"Meninggal"},{"ID":315,"DATE":"10 Desember 2018","CITY":"Tinombo","PROVINCE":"Sulawesi Tengah","PERSECUTOR":"Oknum Polsek Tinombo Selatan","VICTIM":"Rahmat (22)","NUMBER_OF_VICTIM":1,"CASE":"Narkoba","METODE":"Dipukul","METODE_PENYIKSAAN":"Korban sebelumnya ditangkap bersama keempat rekannya yaitu Tiar, Ical, Refil dan Upik karena ditemukan alat isap narkoba jenis sabu-sabu di dalam kamar korban.Menurut Tiar, salah satu pelaku yang ikut ditangkap mengatakan, korban ditelanjangi kemudian dipukul dan diinjak oleh salah seorang personel kepolisian berpakaian preman di dalam kantor Polsek Tinombo Selatan.","EFFECT":"Meninggal"},{"ID":316,"DATE":"23 Desember 2018","CITY":"Batam","PROVINCE":"Kepulauan Riau","PERSECUTOR":"Oknum Polsek Batam","VICTIM":"R 15","NUMBER_OF_VICTIM":1,"CASE":"Narkoba","METODE":"Dipukul","METODE_PENYIKSAAN":"Korban dipukul pada bagian kepala hingga tidak sadarkan diri","EFFECT":"Luka"}]